{
  "name": "Bess Beck",
  "age": 21,
  "address": {
    "street": "Dulhih Trail",
    "city": "Tobonra",
    "state": "MA",
    "zip": "58123"
  },
  "contact": {
    "phone": "(761) 449-7061",
    "servicePhone": "800346685"
  },
  "birthday": "1987-11-23T08:20:41.585Z",
  "ip": "194.86.65.85",
  "foo": "bar",
  "profile": {
    "about": "Kaejumor raile vec belmac johe pujad rilfo cub kobuslos seh reehotat he adsa vaifo tuhfi jufturod mipa zagpeur. Apuiw avokoguf vusaw nid wizap akeva izacibe amogiv agoru wu walgodle jeevesur suwhof hisorwo. Hap wik ofcantac hup cun da wo suog ba niz dejule ab dokase ef luukrom. Pa titcafnip rilpigsel danul ti ra ohemu jemwurow fimfap dogi torimu bihel jeja zizco. Gujkeb duv vima fad atkinug lamhepzu apa vargob terehjog cigwir jubnaf uppic lo. Joznelsi jatjiw jeumegif ru hi dudoz wavig wucoj sumuuz uveh goctip fafud ta bacu mi jesehi.",
    "bio": "Pojelse agfuwtiw hejedu kojo lozicpon rohsov juvutu riv gub nawu ho eze wic dat nofopu okhurof. Efpak opoetvib zu juhpi rumdov nirretah febi bedfabwa we rep cuvnal woconic zamcinu co kewfejok lohur ref ivoozaceb. Goma esutodsi jeceso ahionomuz sivemugu uh tis ihiahius iccub ha dovbiw hagkavmet pacutpo igoteec hucuwi majewiv we. Duakiese cowiput sevme vawvi colewuvi atota udik jugbi suageefu ko leganuc jocef sodvad boghik ja hurheine civebo."
  },
  "apiKey": "ee555b9cddeb6919a8f03004f289877e8d17bec9c2c05358545d573d86b3644f",
  "currency": {
    "code": "MRO",
    "name": "Mauritania Ouguiya"
  }
}